markit_gateway/__init__.py
markit_gateway/__main__.py
markit_gateway/config.py
markit_gateway/utils.py
markit_gateway/cmd/__init__.py
markit_gateway/cmd/control.py
markit_gateway/cmd/easy_setup.py
markit_gateway/cmd/portal.py
markit_gateway/common/IMUParser.py
markit_gateway/common/__init__.py
markit_gateway/common/render.py
markit_gateway/common/repo.py
markit_gateway/common/tcp.py
markit_gateway/functional/__init__.py
markit_gateway/functional/align.py
markit_gateway/functional/convert.py
markit_gateway/functional/ellipse.py
markit_gateway/functional/vector.py
markit_gateway/scripts/__init__.py
markit_gateway/scripts/cli.py
markit_gateway/scripts/configure.py
markit_gateway/tasks/__init__.py
markit_gateway/tasks/imu_render_ui.py
markit_gateway/tasks/measure.py
markit_gateway/tasks/tcp_listen.py
markit_gateway/tasks/tcp_process.py
markit_gateway/tasks/obj/__init__.py
markit_gateway-2.0.1.dist-info/METADATA
markit_gateway-2.0.1.dist-info/WHEEL
markit_gateway-2.0.1.dist-info/top_level.txt
markit_gateway-2.0.1.dist-info/RECORD
